{
    "container_type": "Author",
    "filled": [
        "basics",
        "indices",
        "counts",
        "coauthors",
        "publications",
        "public_access"
    ],
    "scholar_id": "mF4nMFoAAAAJ",
    "source": "AUTHOR_PROFILE_PAGE",
    "name": "CECILIA PERRET",
    "affiliation": "Profesor de Medicina. Pontificia Universidad Cat\u00f3lica de Chile",
    "organization": 7459009050823923954,
    "interests": [
        "Infectolog\u00eda Pedi\u00e1trica"
    ],
    "email_domain": "@uc.cl",
    "citedby": 1752,
    "citedby5y": 759,
    "hindex": 21,
    "hindex5y": 14,
    "i10index": 41,
    "i10index5y": 20,
    "cites_per_year": {
        "2002": 10,
        "2003": 12,
        "2004": 15,
        "2005": 19,
        "2006": 31,
        "2007": 22,
        "2008": 37,
        "2009": 30,
        "2010": 46,
        "2011": 56,
        "2012": 80,
        "2013": 86,
        "2014": 92,
        "2015": 75,
        "2016": 89,
        "2017": 115,
        "2018": 138,
        "2019": 187,
        "2020": 141,
        "2021": 135,
        "2022": 114,
        "2023": 135,
        "2024": 45
    },
    "coauthors": [],
    "publications": [
        {
            "container_type": "Publication",
            "source": "AUTHOR_PUBLICATION_ENTRY",
            "bib": {
                "title": "Illness in children after international travel: analysis from the GeoSentinel Surveillance Network",
                "pub_year": "2010",
                "citation": "Pediatrics 125 (5), e1072-e1080, 2010"
            },
            "filled": false,
            "author_pub_id": "mF4nMFoAAAAJ:vV6vV6tmYwMC",
            "num_citations": 222,
            "citedby_url": "https://scholar.google.com/scholar?oi=bibs&hl=en&cites=17088902942932272335",
            "cites_id": [
                "17088902942932272335"
            ]
        },
        {
            "container_type": "Publication",
            "source": "AUTHOR_PUBLICATION_ENTRY",
            "bib": {
                "title": "Fatal yellow fever in travelers to Brazil, 2018",
                "pub_year": "2018",
                "citation": "MMWR. Morbidity and mortality weekly report 67, 2018"
            },
            "filled": false,
            "author_pub_id": "mF4nMFoAAAAJ:GnPB-g6toBAC",
            "num_citations": 108,
            "citedby_url": "https://scholar.google.com/scholar?oi=bibs&hl=en&cites=15853944242809557850",
            "cites_id": [
                "15853944242809557850"
            ]
        },
        {
            "container_type": "Publication",
            "source": "AUTHOR_PUBLICATION_ENTRY",
            "bib": {
                "title": "Dengue infection during pregnancy and transplacental antibody transfer in Thai mothers",
                "pub_year": "2005",
                "citation": "Journal of Infection 51 (4), 287-293, 2005"
            },
            "filled": false,
            "author_pub_id": "mF4nMFoAAAAJ:_Qo2XoVZTnwC",
            "num_citations": 105,
            "citedby_url": "https://scholar.google.com/scholar?oi=bibs&hl=en&cites=10364464092937884261",
            "cites_id": [
                "10364464092937884261"
            ]
        },
        {
            "container_type": "Publication",
            "source": "AUTHOR_PUBLICATION_ENTRY",
            "bib": {
                "title": "Anaplasma platys in dogs, Chile",
                "pub_year": "2007",
                "citation": "Emerging Infectious Diseases 13 (9), 1392, 2007"
            },
            "filled": false,
            "author_pub_id": "mF4nMFoAAAAJ:lSLTfruPkqcC",
            "num_citations": 99,
            "citedby_url": "https://scholar.google.com/scholar?oi=bibs&hl=en&cites=17086941274425264126",
            "cites_id": [
                "17086941274425264126"
            ]
        },
        {
            "container_type": "Publication",
            "source": "AUTHOR_PUBLICATION_ENTRY",
            "bib": {
                "title": "Travel-associated Zika virus disease acquired in the Americas through February 2016: a GeoSentinel analysis",
                "pub_year": "2017",
                "citation": "Annals of internal medicine 166 (2), 99-108, 2017"
            },
            "filled": false,
            "author_pub_id": "mF4nMFoAAAAJ:YFjsv_pBGBYC",
            "num_citations": 83,
            "citedby_url": "https://scholar.google.com/scholar?oi=bibs&hl=en&cites=15154716352103774133",
            "cites_id": [
                "15154716352103774133"
            ]
        },
        {
            "container_type": "Publication",
            "source": "AUTHOR_PUBLICATION_ENTRY",
            "bib": {
                "title": "Treatment of ciguatera poisoning with gabapentin",
                "pub_year": "2001",
                "citation": "New England Journal of Medicine 344 (9), 692-693, 2001"
            },
            "filled": false,
            "author_pub_id": "mF4nMFoAAAAJ:70eg2SAEIzsC",
            "num_citations": 82,
            "citedby_url": "https://scholar.google.com/scholar?oi=bibs&hl=en&cites=17332041119466235494",
            "cites_id": [
                "17332041119466235494"
            ]
        },
        {
            "container_type": "Publication",
            "source": "AUTHOR_PUBLICATION_ENTRY",
            "bib": {
                "title": "Sensitivity and kinetics of an NS1-based Zika virus enzyme-linked immunosorbent assay in Zika virus-infected travelers from Israel, the Czech Republic, Italy, Belgium, Germany \u2026",
                "pub_year": "2017",
                "citation": "Journal of Clinical Microbiology 55 (6), 1894-1901, 2017"
            },
            "filled": false,
            "author_pub_id": "mF4nMFoAAAAJ:dhFuZR0502QC",
            "num_citations": 67,
            "citedby_url": "https://scholar.google.com/scholar?oi=bibs&hl=en&cites=7827958272696942762",
            "cites_id": [
                "7827958272696942762"
            ]
        },
        {
            "container_type": "Publication",
            "source": "AUTHOR_PUBLICATION_ENTRY",
            "bib": {
                "title": "Recomendaciones para el manejo de mordeduras ocasionadas por animales",
                "pub_year": "2006",
                "citation": "Revista chilena de infectolog\u00eda 23 (1), 20-34, 2006"
            },
            "filled": false,
            "author_pub_id": "mF4nMFoAAAAJ:YOwf2qJgpHMC",
            "num_citations": 65,
            "citedby_url": "https://scholar.google.com/scholar?oi=bibs&hl=en&cites=6272119548880877170",
            "cites_id": [
                "6272119548880877170"
            ]
        },
        {
            "container_type": "Publication",
            "source": "AUTHOR_PUBLICATION_ENTRY",
            "bib": {
                "title": "Prevalencia y presencia de factores de riesgo de leptospirosis en una poblaci\u00f3n de riesgo de la Regi\u00f3n Metropolitana",
                "pub_year": "2005",
                "citation": "Revista m\u00e9dica de Chile 133 (4), 426-431, 2005"
            },
            "filled": false,
            "author_pub_id": "mF4nMFoAAAAJ:M05iB0D1s5AC",
            "num_citations": 47,
            "citedby_url": "https://scholar.google.com/scholar?oi=bibs&hl=en&cites=17521095574499232186",
            "cites_id": [
                "17521095574499232186"
            ]
        },
        {
            "container_type": "Publication",
            "source": "AUTHOR_PUBLICATION_ENTRY",
            "bib": {
                "title": "Immunogenicity, safety, and interchangeability of two inactivated hepatitis A vaccines in Chilean children",
                "pub_year": "2008",
                "citation": "International journal of infectious diseases 12 (3), 270-277, 2008"
            },
            "filled": false,
            "author_pub_id": "mF4nMFoAAAAJ:Se3iqnhoufwC",
            "num_citations": 43,
            "citedby_url": "https://scholar.google.com/scholar?oi=bibs&hl=en&cites=3617235835341677906",
            "cites_id": [
                "3617235835341677906"
            ]
        },
        {
            "container_type": "Publication",
            "source": "AUTHOR_PUBLICATION_ENTRY",
            "bib": {
                "title": "Epidemiology of respiratory infections",
                "pub_year": "2020",
                "citation": "Pediatric respiratory diseases: a comprehensive textbook, 263-272, 2020"
            },
            "filled": false,
            "author_pub_id": "mF4nMFoAAAAJ:u-x6o8ySG0sC",
            "num_citations": 41,
            "citedby_url": "https://scholar.google.com/scholar?oi=bibs&hl=en&cites=15033914466879635291",
            "cites_id": [
                "15033914466879635291"
            ]
        },
        {
            "container_type": "Publication",
            "source": "AUTHOR_PUBLICATION_ENTRY",
            "bib": {
                "title": "Latin America: Situation and preparedness facing the multi-country human monkeypox outbreak",
                "pub_year": "2022",
                "citation": "The Lancet Regional Health\u2013Americas 13, 2022"
            },
            "filled": false,
            "author_pub_id": "mF4nMFoAAAAJ:WbkHhVStYXYC",
            "num_citations": 35,
            "citedby_url": "https://scholar.google.com/scholar?oi=bibs&hl=en&cites=9886934910623051005",
            "cites_id": [
                "9886934910623051005"
            ]
        },
        {
            "container_type": "Publication",
            "source": "AUTHOR_PUBLICATION_ENTRY",
            "bib": {
                "title": "Dengue-1 virus isolation during first dengue fever outbreak on Easter Island, Chile",
                "pub_year": "2003",
                "citation": "Emerging Infectious Diseases 9 (11), 1465, 2003"
            },
            "filled": false,
            "author_pub_id": "mF4nMFoAAAAJ:hC7cP41nSMkC",
            "num_citations": 35,
            "citedby_url": "https://scholar.google.com/scholar?oi=bibs&hl=en&cites=8875832321330731777",
            "cites_id": [
                "8875832321330731777"
            ]
        },
        {
            "container_type": "Publication",
            "source": "AUTHOR_PUBLICATION_ENTRY",
            "bib": {
                "title": "Evidencia seroepidemiol\u00f3gica de exposici\u00f3n humana a Anaplasma sp en Santiago, Chile",
                "pub_year": "2008",
                "citation": "Revista chilena de infectolog\u00eda 25 (5), 358-361, 2008"
            },
            "filled": false,
            "author_pub_id": "mF4nMFoAAAAJ:iH-uZ7U-co4C",
            "num_citations": 31,
            "citedby_url": "https://scholar.google.com/scholar?oi=bibs&hl=en&cites=11207228762344135537,339701297668767437",
            "cites_id": [
                "11207228762344135537",
                "339701297668767437"
            ]
        },
        {
            "container_type": "Publication",
            "source": "AUTHOR_PUBLICATION_ENTRY",
            "bib": {
                "title": "Yellow fever in Brazil: Epidemiological aspects and implications for travelers",
                "pub_year": "2018",
                "citation": "Travel medicine and infectious disease 23, 1-3, 2018"
            },
            "filled": false,
            "author_pub_id": "mF4nMFoAAAAJ:d1gkVwhDpl0C",
            "num_citations": 26,
            "citedby_url": "https://scholar.google.com/scholar?oi=bibs&hl=en&cites=323482535910654090",
            "cites_id": [
                "323482535910654090"
            ]
        },
        {
            "container_type": "Publication",
            "source": "AUTHOR_PUBLICATION_ENTRY",
            "bib": {
                "title": "Recomendaciones para el cuidado y manejo responsable de mascotas y su impacto en salud humana",
                "pub_year": "2005",
                "citation": "Soc Chil Infec, 24-8, 2005"
            },
            "filled": false,
            "author_pub_id": "mF4nMFoAAAAJ:_FxGoFyzp5QC",
            "num_citations": 26,
            "citedby_url": "https://scholar.google.com/scholar?oi=bibs&hl=en&cites=3024381663299870751",
            "cites_id": [
                "3024381663299870751"
            ]
        },
        {
            "container_type": "Publication",
            "source": "AUTHOR_PUBLICATION_ENTRY",
            "bib": {
                "title": "Manual de pediatr\u00eda",
                "pub_year": "2018",
                "citation": "Fondo de Innovaci\u00f3n Docente, INNOVADOC, de la Pontificia Universidad \u2026, 2018"
            },
            "filled": false,
            "author_pub_id": "mF4nMFoAAAAJ:abG-DnoFyZgC",
            "num_citations": 25,
            "citedby_url": "https://scholar.google.com/scholar?oi=bibs&hl=en&cites=5321724168472584136",
            "cites_id": [
                "5321724168472584136"
            ]
        },
        {
            "container_type": "Publication",
            "source": "AUTHOR_PUBLICATION_ENTRY",
            "bib": {
                "title": "Zika among international travellers presenting to GeoSentinel sites, 2012\u20132019: implications for clinical practice",
                "pub_year": "2020",
                "citation": "Journal of travel medicine 27 (4), taaa061, 2020"
            },
            "filled": false,
            "author_pub_id": "mF4nMFoAAAAJ:4DMP91E08xMC",
            "num_citations": 24,
            "citedby_url": "https://scholar.google.com/scholar?oi=bibs&hl=en&cites=16986189945662805330",
            "cites_id": [
                "16986189945662805330"
            ]
        },
        {
            "container_type": "Publication",
            "source": "AUTHOR_PUBLICATION_ENTRY",
            "bib": {
                "title": "Risk factors and frequency of positive antibodies for leptospirosis in a sub urban population near Santiago",
                "pub_year": "2005",
                "citation": "Revista Medica de Chile 133 (4), 426-431, 2005"
            },
            "filled": false,
            "author_pub_id": "mF4nMFoAAAAJ:u9iWguZQMMsC",
            "num_citations": 24,
            "citedby_url": "https://scholar.google.com/scholar?oi=bibs&hl=en&cites=15585544357564657551",
            "cites_id": [
                "15585544357564657551"
            ]
        },
        {
            "container_type": "Publication",
            "source": "AUTHOR_PUBLICATION_ENTRY",
            "bib": {
                "title": "\u00c1ntrax (carbunco)",
                "pub_year": "2001",
                "citation": "Revista chilena de infectolog\u00eda 18 (4), 291-299, 2001"
            },
            "filled": false,
            "author_pub_id": "mF4nMFoAAAAJ:r0BpntZqJG4C",
            "num_citations": 24,
            "citedby_url": "https://scholar.google.com/scholar?oi=bibs&hl=en&cites=11145855406277302672",
            "cites_id": [
                "11145855406277302672"
            ]
        },
        {
            "container_type": "Publication",
            "source": "AUTHOR_PUBLICATION_ENTRY",
            "bib": {
                "title": "Evaluaci\u00f3n de m\u00e9todos diagn\u00f3sticos para s\u00edfilis cong\u00e9nita",
                "pub_year": "2000",
                "citation": "Revista chilena de infectolog\u00eda 17 (4), 289-296, 2000"
            },
            "filled": false,
            "author_pub_id": "mF4nMFoAAAAJ:M3ejUd6NZC8C",
            "num_citations": 21,
            "citedby_url": "https://scholar.google.com/scholar?oi=bibs&hl=en&cites=6782094029023266020",
            "cites_id": [
                "6782094029023266020"
            ]
        },
        {
            "container_type": "Publication",
            "source": "AUTHOR_PUBLICATION_ENTRY",
            "bib": {
                "title": "Human bocavirus in Chile: clinical characteristics and epidemiological profile in children with acute respiratory tract infections",
                "pub_year": "2011",
                "citation": "Revista chilena de infectologia: organo oficial de la Sociedad Chilena de \u2026, 2011"
            },
            "filled": false,
            "author_pub_id": "mF4nMFoAAAAJ:geHnlv5EZngC",
            "num_citations": 19,
            "citedby_url": "https://scholar.google.com/scholar?oi=bibs&hl=en&cites=12262931668186995733",
            "cites_id": [
                "12262931668186995733"
            ]
        },
        {
            "container_type": "Publication",
            "source": "AUTHOR_PUBLICATION_ENTRY",
            "bib": {
                "title": "Complicaciones en ni\u00f1os con varicela en cuatro hospitales de Santiago-Chile: Espectro cl\u00ednico y estimaci\u00f3n de costos directos",
                "pub_year": "2001",
                "citation": "Revista m\u00e9dica de Chile 129 (4), 397-404, 2001"
            },
            "filled": false,
            "author_pub_id": "mF4nMFoAAAAJ:ns9cj8rnVeAC",
            "num_citations": 19,
            "citedby_url": "https://scholar.google.com/scholar?oi=bibs&hl=en&cites=16269445523449725451",
            "cites_id": [
                "16269445523449725451"
            ]
        },
        {
            "container_type": "Publication",
            "source": "AUTHOR_PUBLICATION_ENTRY",
            "bib": {
                "title": "Yellow fever reemergence in Venezuela\u2013implications for international travelers and Latin American countries during the COVID-19 pandemic",
                "pub_year": "2021",
                "citation": "Travel medicine and infectious disease 44, 102192, 2021"
            },
            "filled": false,
            "author_pub_id": "mF4nMFoAAAAJ:dshw04ExmUIC",
            "num_citations": 18,
            "citedby_url": "https://scholar.google.com/scholar?oi=bibs&hl=en&cites=10819747099746800361",
            "cites_id": [
                "10819747099746800361"
            ]
        },
        {
            "container_type": "Publication",
            "source": "AUTHOR_PUBLICATION_ENTRY",
            "bib": {
                "title": "Brotes de salmonelosis y el tama\u00f1o y rol del Estado en Chile",
                "pub_year": "2012",
                "citation": "Revista chilena de infectolog\u00eda 29 (2), 207-214, 2012"
            },
            "filled": false,
            "author_pub_id": "mF4nMFoAAAAJ:0EnyYjriUFMC",
            "num_citations": 17,
            "citedby_url": "https://scholar.google.com/scholar?oi=bibs&hl=en&cites=4538121279304292229",
            "cites_id": [
                "4538121279304292229"
            ]
        },
        {
            "container_type": "Publication",
            "source": "AUTHOR_PUBLICATION_ENTRY",
            "bib": {
                "title": "Fuente de infecci\u00f3n de Bordetella pertussis en lactantes hospitalizados por coqueluche",
                "pub_year": "2011",
                "citation": "Revista m\u00e9dica de Chile 139 (4), 448-454, 2011"
            },
            "filled": false,
            "author_pub_id": "mF4nMFoAAAAJ:UeHWp8X0CEIC",
            "num_citations": 17,
            "citedby_url": "https://scholar.google.com/scholar?oi=bibs&hl=en&cites=805059081309750165",
            "cites_id": [
                "805059081309750165"
            ]
        },
        {
            "container_type": "Publication",
            "source": "AUTHOR_PUBLICATION_ENTRY",
            "bib": {
                "title": "Refractory enteric amebiasis in pediatric patients with acute graft-versus-host disease after allogeneic bone marrow transplantation",
                "pub_year": "2000",
                "citation": "Journal of pediatric gastroenterology and nutrition 31 (1), 86-90, 2000"
            },
            "filled": false,
            "author_pub_id": "mF4nMFoAAAAJ:mB3voiENLucC",
            "num_citations": 17,
            "citedby_url": "https://scholar.google.com/scholar?oi=bibs&hl=en&cites=8968799698468992393",
            "cites_id": [
                "8968799698468992393"
            ]
        },
        {
            "container_type": "Publication",
            "source": "AUTHOR_PUBLICATION_ENTRY",
            "bib": {
                "title": "Salmonellosis outbreaks and the size and role of the Chilean State",
                "pub_year": "2012",
                "citation": "Revista chilena de infectologia: organo oficial de la Sociedad Chilena de \u2026, 2012"
            },
            "filled": false,
            "author_pub_id": "mF4nMFoAAAAJ:ZeXyd9-uunAC",
            "num_citations": 16,
            "citedby_url": "https://scholar.google.com/scholar?oi=bibs&hl=en&cites=8391932323776780403",
            "cites_id": [
                "8391932323776780403"
            ]
        },
        {
            "container_type": "Publication",
            "source": "AUTHOR_PUBLICATION_ENTRY",
            "bib": {
                "title": "Source of infection in young infants hospitalized with Bordetella pertussis",
                "pub_year": "2011",
                "citation": "Revista Medica de Chile 139 (4), 448-454, 2011"
            },
            "filled": false,
            "author_pub_id": "mF4nMFoAAAAJ:W7OEmFMy1HYC",
            "num_citations": 16,
            "citedby_url": "https://scholar.google.com/scholar?oi=bibs&hl=en&cites=1624652873055009340",
            "cites_id": [
                "1624652873055009340"
            ]
        },
        {
            "container_type": "Publication",
            "source": "AUTHOR_PUBLICATION_ENTRY",
            "bib": {
                "title": "Influenza: reemergencia de una antigua enfermedad y el potencial riesgo de una nueva pandemia",
                "pub_year": "2005",
                "citation": "Revista chilena de infectolog\u00eda 22 (1), 75-88, 2005"
            },
            "filled": false,
            "author_pub_id": "mF4nMFoAAAAJ:eQOLeE2rZwMC",
            "num_citations": 16,
            "citedby_url": "https://scholar.google.com/scholar?oi=bibs&hl=en&cites=1968992122416555330",
            "cites_id": [
                "1968992122416555330"
            ]
        },
        {
            "container_type": "Publication",
            "source": "AUTHOR_PUBLICATION_ENTRY",
            "bib": {
                "title": "Metapneumovirus humano como causa de hospitalizaci\u00f3n en ni\u00f1os bajo 3 a\u00f1os de edad, con infecci\u00f3n respiratoria aguda, durante el a\u00f1o 2004",
                "pub_year": "2007",
                "citation": "Revista chilena de infectolog\u00eda 24 (1), 19-26, 2007"
            },
            "filled": false,
            "author_pub_id": "mF4nMFoAAAAJ:_kc_bZDykSQC",
            "num_citations": 14,
            "citedby_url": "https://scholar.google.com/scholar?oi=bibs&hl=en&cites=6359477251863219357",
            "cites_id": [
                "6359477251863219357"
            ]
        },
        {
            "container_type": "Publication",
            "source": "AUTHOR_PUBLICATION_ENTRY",
            "bib": {
                "title": "Fiebre amarilla",
                "pub_year": "2001",
                "citation": "Rev. chil. infectol, 64-8, 2001"
            },
            "filled": false,
            "author_pub_id": "mF4nMFoAAAAJ:isC4tDSrTZIC",
            "num_citations": 14,
            "citedby_url": "https://scholar.google.com/scholar?oi=bibs&hl=en&cites=12415953179114284352",
            "cites_id": [
                "12415953179114284352"
            ]
        },
        {
            "container_type": "Publication",
            "source": "AUTHOR_PUBLICATION_ENTRY",
            "bib": {
                "title": "Inactivated vaccine-induced SARS-CoV-2 variant-specific immunity in children",
                "pub_year": "2022",
                "citation": "Mbio 13 (6), e01311-22, 2022"
            },
            "filled": false,
            "author_pub_id": "mF4nMFoAAAAJ:vRqMK49ujn8C",
            "num_citations": 13,
            "citedby_url": "https://scholar.google.com/scholar?oi=bibs&hl=en&cites=9081477669876265005",
            "cites_id": [
                "9081477669876265005"
            ]
        },
        {
            "container_type": "Publication",
            "source": "AUTHOR_PUBLICATION_ENTRY",
            "bib": {
                "title": "Aporte de la biolog\u00eda molecular en el diagn\u00f3stico de infecciones respiratorias agudas",
                "pub_year": "2016",
                "citation": "Revista chilena de enfermedades respiratorias 32 (4), 224-232, 2016"
            },
            "filled": false,
            "author_pub_id": "mF4nMFoAAAAJ:3s1wT3WcHBgC",
            "num_citations": 13,
            "citedby_url": "https://scholar.google.com/scholar?oi=bibs&hl=en&cites=18436654993252385271",
            "cites_id": [
                "18436654993252385271"
            ]
        },
        {
            "container_type": "Publication",
            "source": "AUTHOR_PUBLICATION_ENTRY",
            "bib": {
                "title": "Complications in children with varicella in 4 hospitals in Santiago, Chile: clinical spectrum and estimation of direct costs",
                "pub_year": "2001",
                "citation": "Revista Medica de Chile 129 (4), 397-404, 2001"
            },
            "filled": false,
            "author_pub_id": "mF4nMFoAAAAJ:rO6llkc54NcC",
            "num_citations": 13,
            "citedby_url": "https://scholar.google.com/scholar?oi=bibs&hl=en&cites=166111440491812818",
            "cites_id": [
                "166111440491812818"
            ]
        },
        {
            "container_type": "Publication",
            "source": "AUTHOR_PUBLICATION_ENTRY",
            "bib": {
                "title": "Age as risk factor for death from pandemic (H1N1) 2009, Chile",
                "pub_year": "2011",
                "citation": "Emerging infectious diseases 17 (7), 1256, 2011"
            },
            "filled": false,
            "author_pub_id": "mF4nMFoAAAAJ:maZDTaKrznsC",
            "num_citations": 11,
            "citedby_url": "https://scholar.google.com/scholar?oi=bibs&hl=en&cites=13116325302453857489",
            "cites_id": [
                "13116325302453857489"
            ]
        },
        {
            "container_type": "Publication",
            "source": "AUTHOR_PUBLICATION_ENTRY",
            "bib": {
                "title": "Disseminated and fatal adenovirus infection in an immunocompromised child",
                "pub_year": "2008",
                "citation": "Revista Chilena de Infectologia: Organo Oficial de la Sociedad Chilena de \u2026, 2008"
            },
            "filled": false,
            "author_pub_id": "mF4nMFoAAAAJ:B3FOqHPlNUQC",
            "num_citations": 11,
            "citedby_url": "https://scholar.google.com/scholar?oi=bibs&hl=en&cites=4621812247341869345",
            "cites_id": [
                "4621812247341869345"
            ]
        },
        {
            "container_type": "Publication",
            "source": "AUTHOR_PUBLICATION_ENTRY",
            "bib": {
                "title": "Perfil cl\u00ednico-epidemiol\u00f3gico de las infecciones por virus respiratorios en adultos hospitalizados durante la estaci\u00f3n de influenza 2004",
                "pub_year": "2006",
                "citation": "Revista chilena de infectolog\u00eda 23 (2), 111-117, 2006"
            },
            "filled": false,
            "author_pub_id": "mF4nMFoAAAAJ:2osOgNQ5qMEC",
            "num_citations": 11,
            "citedby_url": "https://scholar.google.com/scholar?oi=bibs&hl=en&cites=695844199320798028",
            "cites_id": [
                "695844199320798028"
            ]
        },
        {
            "container_type": "Publication",
            "source": "AUTHOR_PUBLICATION_ENTRY",
            "bib": {
                "title": "\u00bf En qu\u00e9 consiste la infecci\u00f3n humana por Virus Zika?",
                "pub_year": "2016",
                "citation": "Revista m\u00e9dica de Chile 144 (10), 1322-1325, 2016"
            },
            "filled": false,
            "author_pub_id": "mF4nMFoAAAAJ:hMod-77fHWUC",
            "num_citations": 10,
            "citedby_url": "https://scholar.google.com/scholar?oi=bibs&hl=en&cites=14627938918627170996",
            "cites_id": [
                "14627938918627170996"
            ]
        },
        {
            "container_type": "Publication",
            "source": "AUTHOR_PUBLICATION_ENTRY",
            "bib": {
                "title": "Many respiratory viruses have temporal association with meningococcal disease",
                "pub_year": "2015",
                "citation": "Allergologia et Immunopathologia 43 (5), 487-492, 2015"
            },
            "filled": false,
            "author_pub_id": "mF4nMFoAAAAJ:u_35RYKgDlwC",
            "num_citations": 10,
            "citedby_url": "https://scholar.google.com/scholar?oi=bibs&hl=en&cites=2071033671401782034",
            "cites_id": [
                "2071033671401782034"
            ]
        },
        {
            "container_type": "Publication",
            "source": "AUTHOR_PUBLICATION_ENTRY",
            "bib": {
                "title": "Tratamiento antimicrobiano abreviado de infecciones respiratorias altas en pediatr\u00eda",
                "pub_year": "2002",
                "citation": "Revista chilena de infectolog\u00eda 19 (1), 49-53, 2002"
            },
            "filled": false,
            "author_pub_id": "mF4nMFoAAAAJ:aqlVkmm33-oC",
            "num_citations": 10,
            "citedby_url": "https://scholar.google.com/scholar?oi=bibs&hl=en&cites=6784908871571675642",
            "cites_id": [
                "6784908871571675642"
            ]
        },
        {
            "container_type": "Publication",
            "source": "AUTHOR_PUBLICATION_ENTRY",
            "bib": {
                "title": "Emergent pneumonia in children",
                "pub_year": "2021",
                "citation": "Frontiers in Pediatrics 9, 676296, 2021"
            },
            "filled": false,
            "author_pub_id": "mF4nMFoAAAAJ:xtRiw3GOFMkC",
            "num_citations": 9,
            "citedby_url": "https://scholar.google.com/scholar?oi=bibs&hl=en&cites=5518110665310341159",
            "cites_id": [
                "5518110665310341159"
            ]
        },
        {
            "container_type": "Publication",
            "source": "AUTHOR_PUBLICATION_ENTRY",
            "bib": {
                "title": "Etiolog\u00eda del s\u00edndrome coquelucho\u00eddeo y rendimiento de las t\u00e9cnicas para el diagn\u00f3stico de bordetella pertussis en pacientes hospitalizados",
                "pub_year": "1999",
                "citation": "Rev. chil. infectol, 17-26, 1999"
            },
            "filled": false,
            "author_pub_id": "mF4nMFoAAAAJ:ULOm3_A8WrAC",
            "num_citations": 9,
            "citedby_url": "https://scholar.google.com/scholar?oi=bibs&hl=en&cites=16991793775879359654",
            "cites_id": [
                "16991793775879359654"
            ]
        },
        {
            "container_type": "Publication",
            "source": "AUTHOR_PUBLICATION_ENTRY",
            "bib": {
                "title": "Ventilaci\u00f3n oscilatoria de alta frecuencia en ni\u00f1os con s\u00edndrome de dificultad respiratoria\" del adulto\"",
                "pub_year": "1998",
                "citation": "Revista chilena de pediatr\u00eda 69 (4), 142-147, 1998"
            },
            "filled": false,
            "author_pub_id": "mF4nMFoAAAAJ:UxriW0iASnsC",
            "num_citations": 9,
            "citedby_url": "https://scholar.google.com/scholar?oi=bibs&hl=en&cites=9283885294382793838,8688119280409682393",
            "cites_id": [
                "9283885294382793838",
                "8688119280409682393"
            ]
        },
        {
            "container_type": "Publication",
            "source": "AUTHOR_PUBLICATION_ENTRY",
            "bib": {
                "title": "A cluster randomized trial of interferon \u00df-1a for the reduction of transmission of SARS-Cov-2: protocol for the Containing Coronavirus Disease 19 trial (ConCorD-19)",
                "pub_year": "2021",
                "citation": "BMC Infectious Diseases 21, 1-11, 2021"
            },
            "filled": false,
            "author_pub_id": "mF4nMFoAAAAJ:KxtntwgDAa4C",
            "num_citations": 8,
            "citedby_url": "https://scholar.google.com/scholar?oi=bibs&hl=en&cites=12177838049828555248",
            "cites_id": [
                "12177838049828555248"
            ]
        },
        {
            "container_type": "Publication",
            "source": "AUTHOR_PUBLICATION_ENTRY",
            "bib": {
                "title": "Comparaci\u00f3n entre dos m\u00e9todos de determinaci\u00f3n del test del sudor en el diagn\u00f3stico de la fibrosis qu\u00edstica",
                "pub_year": "1999",
                "citation": "Revista chilena de pediatr\u00eda 70 (4), 281-287, 1999"
            },
            "filled": false,
            "author_pub_id": "mF4nMFoAAAAJ:qjMakFHDy7sC",
            "num_citations": 8,
            "citedby_url": "https://scholar.google.com/scholar?oi=bibs&hl=en&cites=775020676310852041",
            "cites_id": [
                "775020676310852041"
            ]
        },
        {
            "container_type": "Publication",
            "source": "AUTHOR_PUBLICATION_ENTRY",
            "bib": {
                "title": "Cluster of imported vivax malaria in travelers returning from Peru",
                "pub_year": "2015",
                "citation": "Journal of travel medicine 22 (6), 415-418, 2015"
            },
            "filled": false,
            "author_pub_id": "mF4nMFoAAAAJ:7PzlFSSx8tAC",
            "num_citations": 7,
            "citedby_url": "https://scholar.google.com/scholar?oi=bibs&hl=en&cites=7970531935748476075",
            "cites_id": [
                "7970531935748476075"
            ]
        },
        {
            "container_type": "Publication",
            "source": "AUTHOR_PUBLICATION_ENTRY",
            "bib": {
                "title": "Vacuna anti-pertussis para uso en adolescentes y adultos",
                "pub_year": "2006",
                "citation": "Revista chilena de infectolog\u00eda 23 (3), 257-260, 2006"
            },
            "filled": false,
            "author_pub_id": "mF4nMFoAAAAJ:HoB7MX3m0LUC",
            "num_citations": 7,
            "citedby_url": "https://scholar.google.com/scholar?oi=bibs&hl=en&cites=18050896277873394727",
            "cites_id": [
                "18050896277873394727"
            ]
        },
        {
            "container_type": "Publication",
            "source": "AUTHOR_PUBLICATION_ENTRY",
            "bib": {
                "title": "Vigilancia de virus respiratorios. Temporada 2004",
                "pub_year": "2004",
                "citation": "Cuadernos M\u00e9dico Sociales 44 (3), 139-143, 2004"
            },
            "filled": false,
            "author_pub_id": "mF4nMFoAAAAJ:RHpTSmoSYBkC",
            "num_citations": 7,
            "citedby_url": "https://scholar.google.com/scholar?oi=bibs&hl=en&cites=10364730635247340095",
            "cites_id": [
                "10364730635247340095"
            ]
        },
        {
            "container_type": "Publication",
            "source": "AUTHOR_PUBLICATION_ENTRY",
            "bib": {
                "title": "Shortage of yellow fever vaccination: a travel medicine emergency for Chilean travellers",
                "pub_year": "2019",
                "citation": "Elsevier Ltd., 2019"
            },
            "filled": false,
            "author_pub_id": "mF4nMFoAAAAJ:IjCSPb-OGe4C",
            "num_citations": 6,
            "citedby_url": "https://scholar.google.com/scholar?oi=bibs&hl=en&cites=1037444869131223702",
            "cites_id": [
                "1037444869131223702"
            ]
        },
        {
            "container_type": "Publication",
            "source": "AUTHOR_PUBLICATION_ENTRY",
            "bib": {
                "title": "Pediatric Respiratory Diseases",
                "pub_year": "2016",
                "citation": "Santiago de Chile: Springer, 2016"
            },
            "filled": false,
            "author_pub_id": "mF4nMFoAAAAJ:LkGwnXOMwfcC",
            "num_citations": 6,
            "citedby_url": "https://scholar.google.com/scholar?oi=bibs&hl=en&cites=4044019731176845215",
            "cites_id": [
                "4044019731176845215"
            ]
        },
        {
            "container_type": "Publication",
            "source": "AUTHOR_PUBLICATION_ENTRY",
            "bib": {
                "title": "Influenza pand\u00e9mica a un a\u00f1o de la primera ola:\u00bf Qu\u00e9 podemos decir ahora?",
                "pub_year": "2010",
                "citation": "Revista chilena de infectolog\u00eda 27 (2), 144-147, 2010"
            },
            "filled": false,
            "author_pub_id": "mF4nMFoAAAAJ:qUcmZB5y_30C",
            "num_citations": 6,
            "citedby_url": "https://scholar.google.com/scholar?oi=bibs&hl=en&cites=8585301186088842678",
            "cites_id": [
                "8585301186088842678"
            ]
        },
        {
            "container_type": "Publication",
            "source": "AUTHOR_PUBLICATION_ENTRY",
            "bib": {
                "title": "Clinical and epidemiological characteristics of respiratory virus infections among adults hospitalized during 2004 influenza season",
                "pub_year": "2006",
                "citation": "Revista Chilena de Infectologia: Organo Oficial de la Sociedad Chilena de \u2026, 2006"
            },
            "filled": false,
            "author_pub_id": "mF4nMFoAAAAJ:sSrBHYA8nusC",
            "num_citations": 6,
            "citedby_url": "https://scholar.google.com/scholar?oi=bibs&hl=en&cites=8992019960008295858",
            "cites_id": [
                "8992019960008295858"
            ]
        },
        {
            "container_type": "Publication",
            "source": "AUTHOR_PUBLICATION_ENTRY",
            "bib": {
                "title": "Malaria: revisi\u00f3n retrospectiva de 12 casos no aut\u00f3ctonos en Chile",
                "pub_year": "2006",
                "citation": "Revista m\u00e9dica de Chile 134 (4), 421-425, 2006"
            },
            "filled": false,
            "author_pub_id": "mF4nMFoAAAAJ:4TOpqqG69KYC",
            "num_citations": 6,
            "citedby_url": "https://scholar.google.com/scholar?oi=bibs&hl=en&cites=6775630056299363628",
            "cites_id": [
                "6775630056299363628"
            ]
        },
        {
            "container_type": "Publication",
            "source": "AUTHOR_PUBLICATION_ENTRY",
            "bib": {
                "title": "Endocarditis por Streptococcus pneumoniae en ni\u00f1os: Presentaci\u00f3n de un caso cl\u00ednico y revisi\u00f3n de la literatura",
                "pub_year": "2005",
                "citation": "Revista chilena de infectolog\u00eda 22 (4), 361-367, 2005"
            },
            "filled": false,
            "author_pub_id": "mF4nMFoAAAAJ:-f6ydRqryjwC",
            "num_citations": 6,
            "citedby_url": "https://scholar.google.com/scholar?oi=bibs&hl=en&cites=8901818697549113165",
            "cites_id": [
                "8901818697549113165"
            ]
        },
        {
            "container_type": "Publication",
            "source": "AUTHOR_PUBLICATION_ENTRY",
            "bib": {
                "title": "Neumon\u00eda grave causada por Haemophilus influenzae no tipificable en un lactante: reporte de un caso",
                "pub_year": "2005",
                "citation": "Revista chilena de infectolog\u00eda 22 (1), 89-92, 2005"
            },
            "filled": false,
            "author_pub_id": "mF4nMFoAAAAJ:MXK_kJrjxJIC",
            "num_citations": 6,
            "citedby_url": "https://scholar.google.com/scholar?oi=bibs&hl=en&cites=5414399091853742854",
            "cites_id": [
                "5414399091853742854"
            ]
        },
        {
            "container_type": "Publication",
            "source": "AUTHOR_PUBLICATION_ENTRY",
            "bib": {
                "title": "Chikungunya, enfermedad emergente en Am\u00e9rica Latina. Descripci\u00f3n de los primeros casos en Chile",
                "pub_year": "2018",
                "citation": "Revista chilena de infectolog\u00eda 35 (4), 413-419, 2018"
            },
            "filled": false,
            "author_pub_id": "mF4nMFoAAAAJ:ufrVoPGSRksC",
            "num_citations": 5,
            "citedby_url": "https://scholar.google.com/scholar?oi=bibs&hl=en&cites=2735529966985955530",
            "cites_id": [
                "2735529966985955530"
            ]
        },
        {
            "container_type": "Publication",
            "source": "AUTHOR_PUBLICATION_ENTRY",
            "bib": {
                "title": "Sensitivity and kinetics of a NS1-based Zika virus ELISA in Zika infected travelers from Israel, Czech Republic, Italy, Belgium, Germany and Chile",
                "pub_year": "2017",
                "citation": ""
            },
            "filled": false,
            "author_pub_id": "mF4nMFoAAAAJ:O3NaXMp0MMsC",
            "num_citations": 5,
            "citedby_url": "https://scholar.google.com/scholar?oi=bibs&hl=en&cites=16158589978019878208",
            "cites_id": [
                "16158589978019878208"
            ]
        },
        {
            "container_type": "Publication",
            "source": "AUTHOR_PUBLICATION_ENTRY",
            "bib": {
                "title": "Infecciones en viajeros internacionales",
                "pub_year": "2014",
                "citation": "Revista M\u00e9dica Cl\u00ednica Las Condes 25 (3), 565-568, 2014"
            },
            "filled": false,
            "author_pub_id": "mF4nMFoAAAAJ:UebtZRa9Y70C",
            "num_citations": 5,
            "citedby_url": "https://scholar.google.com/scholar?oi=bibs&hl=en&cites=3749442827471273071",
            "cites_id": [
                "3749442827471273071"
            ]
        },
        {
            "container_type": "Publication",
            "source": "AUTHOR_PUBLICATION_ENTRY",
            "bib": {
                "title": "El ni\u00f1o viajero: recomendaciones",
                "pub_year": "2011",
                "citation": "Revista chilena de infectolog\u00eda 28 (2), 153-156, 2011"
            },
            "filled": false,
            "author_pub_id": "mF4nMFoAAAAJ:mVmsd5A6BfQC",
            "num_citations": 5,
            "citedby_url": "https://scholar.google.com/scholar?oi=bibs&hl=en&cites=7270061420210756968",
            "cites_id": [
                "7270061420210756968"
            ]
        },
        {
            "container_type": "Publication",
            "source": "AUTHOR_PUBLICATION_ENTRY",
            "bib": {
                "title": "Influenza pandemic of novel (H1N1) 2009 virus in Chile. How we dealt with the first wave?",
                "pub_year": "2009",
                "citation": "Revista Chilena de Infectologia: Organo Oficial de la Sociedad Chilena de \u2026, 2009"
            },
            "filled": false,
            "author_pub_id": "mF4nMFoAAAAJ:p2g8aNsByqUC",
            "num_citations": 5,
            "citedby_url": "https://scholar.google.com/scholar?oi=bibs&hl=en&cites=11918136106197461887",
            "cites_id": [
                "11918136106197461887"
            ]
        },
        {
            "container_type": "Publication",
            "source": "AUTHOR_PUBLICATION_ENTRY",
            "bib": {
                "title": "Infecci\u00f3n diseminada por adenovirus de curso fatal en un ni\u00f1o inmunocomprometido",
                "pub_year": "2008",
                "citation": "Revista chilena de infectolog\u00eda 25 (2), 127-132, 2008"
            },
            "filled": false,
            "author_pub_id": "mF4nMFoAAAAJ:hFOr9nPyWt4C",
            "num_citations": 5,
            "citedby_url": "https://scholar.google.com/scholar?oi=bibs&hl=en&cites=8923511843388564054",
            "cites_id": [
                "8923511843388564054"
            ]
        },
        {
            "container_type": "Publication",
            "source": "AUTHOR_PUBLICATION_ENTRY",
            "bib": {
                "title": "Human metapneumovirus as hospitalization cause in children under 3 years old with acute respiratory infections during 2004",
                "pub_year": "2007",
                "citation": "Revista Chilena de Infectologia: Organo Oficial de la Sociedad Chilena de \u2026, 2007"
            },
            "filled": false,
            "author_pub_id": "mF4nMFoAAAAJ:OU6Ihb5iCvQC",
            "num_citations": 5,
            "citedby_url": "https://scholar.google.com/scholar?oi=bibs&hl=en&cites=1131937154487343654",
            "cites_id": [
                "1131937154487343654"
            ]
        },
        {
            "container_type": "Publication",
            "source": "AUTHOR_PUBLICATION_ENTRY",
            "bib": {
                "title": "Lactic acidosis and hyperlactatemia",
                "pub_year": "1990",
                "citation": "La Revue du Praticien 40 (22), 2042-2046, 1990"
            },
            "filled": false,
            "author_pub_id": "mF4nMFoAAAAJ:zA6iFVUQeVQC",
            "num_citations": 5,
            "citedby_url": "https://scholar.google.com/scholar?oi=bibs&hl=en&cites=1637811784989976203",
            "cites_id": [
                "1637811784989976203"
            ]
        },
        {
            "container_type": "Publication",
            "source": "AUTHOR_PUBLICATION_ENTRY",
            "bib": {
                "title": "Nouvelle observation d'enc\u00e9phalite \u00e0 tiques en Alsace",
                "pub_year": "1987",
                "citation": "M\u00e9decine et maladies infectieuses 17 (1), 35-37, 1987"
            },
            "filled": false,
            "author_pub_id": "mF4nMFoAAAAJ:cFHS6HbyZ2cC",
            "num_citations": 5,
            "citedby_url": "https://scholar.google.com/scholar?oi=bibs&hl=en&cites=4893222020003597740",
            "cites_id": [
                "4893222020003597740"
            ]
        },
        {
            "container_type": "Publication",
            "source": "AUTHOR_PUBLICATION_ENTRY",
            "bib": {
                "title": "An inactivated SARS-CoV-2 vaccine is safe and induces humoral and cellular immunity against virus variants in healthy children and adolescents in Chile",
                "pub_year": "2022",
                "citation": "medRxiv, 2022.02. 15.22270973, 2022"
            },
            "filled": false,
            "author_pub_id": "mF4nMFoAAAAJ:SP6oXDckpogC",
            "num_citations": 4,
            "citedby_url": "https://scholar.google.com/scholar?oi=bibs&hl=en&cites=7107922511276560337",
            "cites_id": [
                "7107922511276560337"
            ]
        },
        {
            "container_type": "Publication",
            "source": "AUTHOR_PUBLICATION_ENTRY",
            "bib": {
                "title": "Detecci\u00f3n del SARS-CoV-2 mediante RT-qPCR utilizando saliva en pacientes ambulatorios con estudio de COVID-19",
                "pub_year": "2022",
                "citation": "Revista chilena de infectolog\u00eda 39 (4), 372-381, 2022"
            },
            "filled": false,
            "author_pub_id": "mF4nMFoAAAAJ:tS2w5q8j5-wC",
            "num_citations": 4,
            "citedby_url": "https://scholar.google.com/scholar?oi=bibs&hl=en&cites=5169102181657728082",
            "cites_id": [
                "5169102181657728082"
            ]
        },
        {
            "container_type": "Publication",
            "source": "AUTHOR_PUBLICATION_ENTRY",
            "bib": {
                "title": "Evaluation of ELISA-based multiplex peptides for the detection of human serum antibodies induced by Zika virus infection across various countries",
                "pub_year": "2021",
                "citation": "Viruses 13 (7), 1319, 2021"
            },
            "filled": false,
            "author_pub_id": "mF4nMFoAAAAJ:nb7KW1ujOQ8C",
            "num_citations": 4,
            "citedby_url": "https://scholar.google.com/scholar?oi=bibs&hl=en&cites=4843554884471510769",
            "cites_id": [
                "4843554884471510769"
            ]
        },
        {
            "container_type": "Publication",
            "source": "AUTHOR_PUBLICATION_ENTRY",
            "bib": {
                "title": "Asociaci\u00f3n temporal entre la circulaci\u00f3n de virus respiratorios y hospitalizaciones por enfermedad de Kawasaki",
                "pub_year": "2021",
                "citation": "Revista chilena de infectolog\u00eda 38 (2), 152-160, 2021"
            },
            "filled": false,
            "author_pub_id": "mF4nMFoAAAAJ:CHSYGLWDkRkC",
            "num_citations": 4,
            "citedby_url": "https://scholar.google.com/scholar?oi=bibs&hl=en&cites=12833475213296464130",
            "cites_id": [
                "12833475213296464130"
            ]
        },
        {
            "container_type": "Publication",
            "source": "AUTHOR_PUBLICATION_ENTRY",
            "bib": {
                "title": "Infecci\u00f3n at\u00edpica y neurorretinitis por Bartonella henselae en una unidad de hospitalizaci\u00f3n pedi\u00e1trica: comunicaci\u00f3n de tres casos",
                "pub_year": "2020",
                "citation": "Revista chilena de infectolog\u00eda 37 (4), 463-469, 2020"
            },
            "filled": false,
            "author_pub_id": "mF4nMFoAAAAJ:L8Ckcad2t8MC",
            "num_citations": 4,
            "citedby_url": "https://scholar.google.com/scholar?oi=bibs&hl=en&cites=14727641104744739605",
            "cites_id": [
                "14727641104744739605"
            ]
        },
        {
            "container_type": "Publication",
            "source": "AUTHOR_PUBLICATION_ENTRY",
            "bib": {
                "title": "Modelo computacional interactivo, semi-automatizado y de c\u00f3digo abierto aplicado a la vigilancia de virus respiratorios",
                "pub_year": "2020",
                "citation": "Revista chilena de infectolog\u00eda 37 (1), 69-75, 2020"
            },
            "filled": false,
            "author_pub_id": "mF4nMFoAAAAJ:ZHo1McVdvXMC",
            "num_citations": 4,
            "citedby_url": "https://scholar.google.com/scholar?oi=bibs&hl=en&cites=18374361633349238557",
            "cites_id": [
                "18374361633349238557"
            ]
        },
        {
            "container_type": "Publication",
            "source": "AUTHOR_PUBLICATION_ENTRY",
            "bib": {
                "title": "Current topics in chikungunya",
                "pub_year": "2016",
                "citation": "BoD\u2013Books on Demand, 2016"
            },
            "filled": false,
            "author_pub_id": "mF4nMFoAAAAJ:j3f4tGmQtD8C",
            "num_citations": 4,
            "citedby_url": "https://scholar.google.com/scholar?oi=bibs&hl=en&cites=11102804793590780771",
            "cites_id": [
                "11102804793590780771"
            ]
        },
        {
            "container_type": "Publication",
            "source": "AUTHOR_PUBLICATION_ENTRY",
            "bib": {
                "title": "Seroepidemiological evidence of human exposure to Anaplasma sp in Santiago, Chile",
                "pub_year": "2008",
                "citation": "Rev Chil Infectol 25 (5), 358-61, 2008"
            },
            "filled": false,
            "author_pub_id": "mF4nMFoAAAAJ:WF5omc3nYNoC",
            "num_citations": 4,
            "citedby_url": "https://scholar.google.com/scholar?oi=bibs&hl=en&cites=2445501666597951032",
            "cites_id": [
                "2445501666597951032"
            ]
        },
        {
            "container_type": "Publication",
            "source": "AUTHOR_PUBLICATION_ENTRY",
            "bib": {
                "title": "Influenza: the reemergence of an ancient disease and its risk of pandemia",
                "pub_year": "2005",
                "citation": "Revista Chilena de Infectologia: Organo Oficial de la Sociedad Chilena de \u2026, 2005"
            },
            "filled": false,
            "author_pub_id": "mF4nMFoAAAAJ:ldfaerwXgEUC",
            "num_citations": 4,
            "citedby_url": "https://scholar.google.com/scholar?oi=bibs&hl=en&cites=17377046458122994711",
            "cites_id": [
                "17377046458122994711"
            ]
        },
        {
            "container_type": "Publication",
            "source": "AUTHOR_PUBLICATION_ENTRY",
            "bib": {
                "title": "Chikungunya, emerging disease in Latin America. Description of the first cases in Chile",
                "pub_year": "2018",
                "citation": "Revista Chilena de Infectologia: Organo Oficial de la Sociedad Chilena de \u2026, 2018"
            },
            "filled": false,
            "author_pub_id": "mF4nMFoAAAAJ:u5HHmVD_uO8C",
            "num_citations": 3,
            "citedby_url": "https://scholar.google.com/scholar?oi=bibs&hl=en&cites=268085092739277844",
            "cites_id": [
                "268085092739277844"
            ]
        },
        {
            "container_type": "Publication",
            "source": "AUTHOR_PUBLICATION_ENTRY",
            "bib": {
                "title": "Zika virus, guilty or innocent?",
                "pub_year": "2016",
                "citation": "Revista Chilena de Infectologia: Organo Oficial de la Sociedad Chilena de \u2026, 2016"
            },
            "filled": false,
            "author_pub_id": "mF4nMFoAAAAJ:Wp0gIr-vW9MC",
            "num_citations": 3,
            "citedby_url": "https://scholar.google.com/scholar?oi=bibs&hl=en&cites=7181488139690761157",
            "cites_id": [
                "7181488139690761157"
            ]
        },
        {
            "container_type": "Publication",
            "source": "AUTHOR_PUBLICATION_ENTRY",
            "bib": {
                "title": "Bocavirus humano en Chile: caracter\u00edsticas cl\u00ednicas y epidemiol\u00f3gicas en ni\u00f1os con infecciones respiratorias",
                "pub_year": "2011",
                "citation": "Revista chilena de infectolog\u00eda 28 (6), 504-511, 2011"
            },
            "filled": false,
            "author_pub_id": "mF4nMFoAAAAJ:blknAaTinKkC",
            "num_citations": 3,
            "citedby_url": "https://scholar.google.com/scholar?oi=bibs&hl=en&cites=14112313096437797940",
            "cites_id": [
                "14112313096437797940"
            ]
        },
        {
            "container_type": "Publication",
            "source": "AUTHOR_PUBLICATION_ENTRY",
            "bib": {
                "title": "Influenza aviar y riesgo de pandemia",
                "pub_year": "2008",
                "citation": "Revista chilena de pediatr\u00eda 79 (4), 358-363, 2008"
            },
            "filled": false,
            "author_pub_id": "mF4nMFoAAAAJ:JV2RwH3_ST0C",
            "num_citations": 3,
            "citedby_url": "https://scholar.google.com/scholar?oi=bibs&hl=en&cites=13872607039335835764",
            "cites_id": [
                "13872607039335835764"
            ]
        },
        {
            "container_type": "Publication",
            "source": "AUTHOR_PUBLICATION_ENTRY",
            "bib": {
                "title": "Streptococcus pneumoniae (neumococo) resistente en pediatr\u00eda: Tendencia actual",
                "pub_year": "2001",
                "citation": "Revista chilena de pediatr\u00eda 72 (1), 49-51, 2001"
            },
            "filled": false,
            "author_pub_id": "mF4nMFoAAAAJ:RYcK_YlVTxYC",
            "num_citations": 3,
            "citedby_url": "https://scholar.google.com/scholar?oi=bibs&hl=en&cites=17032000676506745239",
            "cites_id": [
                "17032000676506745239"
            ]
        },
        {
            "container_type": "Publication",
            "source": "AUTHOR_PUBLICATION_ENTRY",
            "bib": {
                "title": "Acidose lactique et hyperlactat\u00e9mie",
                "pub_year": "1990",
                "citation": "La Revue du praticien (Paris) 40 (22), 2042-2046, 1990"
            },
            "filled": false,
            "author_pub_id": "mF4nMFoAAAAJ:dfsIfKJdRG4C",
            "num_citations": 3,
            "citedby_url": "https://scholar.google.com/scholar?oi=bibs&hl=en&cites=3362768287452833154",
            "cites_id": [
                "3362768287452833154"
            ]
        },
        {
            "container_type": "Publication",
            "source": "AUTHOR_PUBLICATION_ENTRY",
            "bib": {
                "title": "Intestinal protozoa in returning travellers: a GeoSentinel analysis from 2007 to 2019",
                "pub_year": "2024",
                "citation": "Journal of Travel Medicine, taae010, 2024"
            },
            "filled": false,
            "author_pub_id": "mF4nMFoAAAAJ:Mojj43d5GZwC",
            "num_citations": 2,
            "citedby_url": "https://scholar.google.com/scholar?oi=bibs&hl=en&cites=8501491291294234106",
            "cites_id": [
                "8501491291294234106"
            ]
        },
        {
            "container_type": "Publication",
            "source": "AUTHOR_PUBLICATION_ENTRY",
            "bib": {
                "title": "Yellow fever vaccination for Chilean tourists visiting Brazil. practical considerations",
                "pub_year": "2018",
                "citation": "Rev Chilena Infectol 35 (5), 587-594, 2018"
            },
            "filled": false,
            "author_pub_id": "mF4nMFoAAAAJ:35N4QoGY0k4C",
            "num_citations": 2,
            "citedby_url": "https://scholar.google.com/scholar?oi=bibs&hl=en&cites=17129190451773426346",
            "cites_id": [
                "17129190451773426346"
            ]
        },
        {
            "container_type": "Publication",
            "source": "AUTHOR_PUBLICATION_ENTRY",
            "bib": {
                "title": "Vacuna contra fiebre amarilla para viajeros chilenos a Brasil. Consideraciones pr\u00e1cticas",
                "pub_year": "2018",
                "citation": "Revista chilena de infectolog\u00eda 35 (5), 587-590, 2018"
            },
            "filled": false,
            "author_pub_id": "mF4nMFoAAAAJ:BqipwSGYUEgC",
            "num_citations": 2,
            "citedby_url": "https://scholar.google.com/scholar?oi=bibs&hl=en&cites=15723131310952550469",
            "cites_id": [
                "15723131310952550469"
            ]
        },
        {
            "container_type": "Publication",
            "source": "AUTHOR_PUBLICATION_ENTRY",
            "bib": {
                "title": "Pandemic influenza one year after the first wave: what did we learn?",
                "pub_year": "2010",
                "citation": "Revista chilena de infectologia: organo oficial de la Sociedad Chilena de \u2026, 2010"
            },
            "filled": false,
            "author_pub_id": "mF4nMFoAAAAJ:uWQEDVKXjbEC",
            "num_citations": 2,
            "citedby_url": "https://scholar.google.com/scholar?oi=bibs&hl=en&cites=653994512948058227",
            "cites_id": [
                "653994512948058227"
            ]
        },
        {
            "container_type": "Publication",
            "source": "AUTHOR_PUBLICATION_ENTRY",
            "bib": {
                "title": "Endocarditis caused by Streptococcus pneumoniae in children: case report and review",
                "pub_year": "2005",
                "citation": "Revista Chilena de Infectologia: Organo Oficial de la Sociedad Chilena de \u2026, 2005"
            },
            "filled": false,
            "author_pub_id": "mF4nMFoAAAAJ:4JMBOYKVnBMC",
            "num_citations": 2,
            "citedby_url": "https://scholar.google.com/scholar?oi=bibs&hl=en&cites=10479525930518326269",
            "cites_id": [
                "10479525930518326269"
            ]
        },
        {
            "container_type": "Publication",
            "source": "AUTHOR_PUBLICATION_ENTRY",
            "bib": {
                "title": "Abarca V Katia DPJ et al. \u00c1ntrax (Carbunco)",
                "pub_year": "2001",
                "citation": "Rev chil infectol [Internet][Internet] 18 (4), 291-9, 2001"
            },
            "filled": false,
            "author_pub_id": "mF4nMFoAAAAJ:9ZlFYXVOiuMC",
            "num_citations": 2,
            "citedby_url": "https://scholar.google.com/scholar?oi=bibs&hl=en&cites=7470246060479231274",
            "cites_id": [
                "7470246060479231274"
            ]
        },
        {
            "container_type": "Publication",
            "source": "AUTHOR_PUBLICATION_ENTRY",
            "bib": {
                "title": "Peritonitis espont\u00e1nea por Pasteurella multocida en un ni\u00f1o: reporte de un caso y revisi\u00f3n de la literatura",
                "pub_year": "1998",
                "citation": "Rev. chil. infectol, 193-7, 1998"
            },
            "filled": false,
            "author_pub_id": "mF4nMFoAAAAJ:2P1L_qKh6hAC",
            "num_citations": 2,
            "citedby_url": "https://scholar.google.com/scholar?oi=bibs&hl=en&cites=17373310845257075213",
            "cites_id": [
                "17373310845257075213"
            ]
        },
        {
            "container_type": "Publication",
            "source": "AUTHOR_PUBLICATION_ENTRY",
            "bib": {
                "title": "Different Safety Pattern of an Inactivated SARS-CoV-2 Vaccine (CoronaVac\u00ae) According to Age Group in a Pediatric Population from 3 to 17 Years Old, in an Open \u2026",
                "pub_year": "2023",
                "citation": "Vaccines 11 (10), 1526, 2023"
            },
            "filled": false,
            "author_pub_id": "mF4nMFoAAAAJ:wbdj-CoPYUoC",
            "num_citations": 1,
            "citedby_url": "https://scholar.google.com/scholar?oi=bibs&hl=en&cites=9489529793714560394",
            "cites_id": [
                "9489529793714560394"
            ]
        },
        {
            "container_type": "Publication",
            "source": "AUTHOR_PUBLICATION_ENTRY",
            "bib": {
                "title": "Interferon \u03b2-1a ring prophylaxis to reduce household transmission of SARS-CoV-2: a cluster randomised clinical trial",
                "pub_year": "2023",
                "citation": "EClinicalMedicine 62, 2023"
            },
            "filled": false,
            "author_pub_id": "mF4nMFoAAAAJ:q3oQSFYPqjQC",
            "num_citations": 1,
            "citedby_url": "https://scholar.google.com/scholar?oi=bibs&hl=en&cites=9237599345723542066",
            "cites_id": [
                "9237599345723542066"
            ]
        },
        {
            "container_type": "Publication",
            "source": "AUTHOR_PUBLICATION_ENTRY",
            "bib": {
                "title": "Temporal association between the circulation of respiratory viruses and hospitalizations due to Kawasaki disease",
                "pub_year": "2021",
                "citation": "Revista Chilena de Infectologia: Organo Oficial de la Sociedad Chilena de \u2026, 2021"
            },
            "filled": false,
            "author_pub_id": "mF4nMFoAAAAJ:P5F9QuxV20EC",
            "num_citations": 1,
            "citedby_url": "https://scholar.google.com/scholar?oi=bibs&hl=en&cites=11616979009410570699",
            "cites_id": [
                "11616979009410570699"
            ]
        },
        {
            "container_type": "Publication",
            "source": "AUTHOR_PUBLICATION_ENTRY",
            "bib": {
                "title": "Pneumonia Caused by Emerging Viral Agents",
                "pub_year": "2020",
                "citation": "Pediatric Respiratory Diseases: A Comprehensive Textbook, 335-341, 2020"
            },
            "filled": false,
            "author_pub_id": "mF4nMFoAAAAJ:RGFaLdJalmkC",
            "num_citations": 1,
            "citedby_url": "https://scholar.google.com/scholar?oi=bibs&hl=en&cites=4997428807433909492",
            "cites_id": [
                "4997428807433909492"
            ]
        },
        {
            "container_type": "Publication",
            "source": "AUTHOR_PUBLICATION_ENTRY",
            "bib": {
                "title": "Zika virus disease among travelers returning from the Americas between January 2013 and February 2016: a geosentinel analysis",
                "pub_year": "2017",
                "citation": "American Journal of Tropical Medicine and Hygiene 95 (5, S), 218, 2017"
            },
            "filled": false,
            "author_pub_id": "mF4nMFoAAAAJ:HDshCWvjkbEC",
            "num_citations": 1,
            "citedby_url": "https://scholar.google.com/scholar?oi=bibs&hl=en&cites=9237053312432608939",
            "cites_id": [
                "9237053312432608939"
            ]
        },
        {
            "container_type": "Publication",
            "source": "AUTHOR_PUBLICATION_ENTRY",
            "bib": {
                "title": "Recommendations for Chilean travelers to the FIFA World Cup 2014 in Brazil",
                "pub_year": "2014",
                "citation": "Revista Chilena de Infectologia: Organo Oficial de la Sociedad Chilena de \u2026, 2014"
            },
            "filled": false,
            "author_pub_id": "mF4nMFoAAAAJ:zYLM7Y9cAGgC",
            "num_citations": 1,
            "citedby_url": "https://scholar.google.com/scholar?oi=bibs&hl=en&cites=1269709943980707053",
            "cites_id": [
                "1269709943980707053"
            ]
        },
        {
            "container_type": "Publication",
            "source": "AUTHOR_PUBLICATION_ENTRY",
            "bib": {
                "title": "The travelling child: recommendations",
                "pub_year": "2011",
                "citation": "Revista chilena de infectologia: organo oficial de la Sociedad Chilena de \u2026, 2011"
            },
            "filled": false,
            "author_pub_id": "mF4nMFoAAAAJ:NhqRSupF_l8C",
            "num_citations": 1,
            "citedby_url": "https://scholar.google.com/scholar?oi=bibs&hl=en&cites=18365900743328555511",
            "cites_id": [
                "18365900743328555511"
            ]
        },
        {
            "container_type": "Publication",
            "source": "AUTHOR_PUBLICATION_ENTRY",
            "bib": {
                "title": "Evaluation of direct immunofluorescent assay (DFA) and rapid antigen test (RAT) for diagnosis of new pandemic influenza A H1N1 2009 (FLU AH1N1) during first wave in Santiago, Chile",
                "pub_year": "2010",
                "citation": "International Journal of Infectious Diseases 14, e100-e101, 2010"
            },
            "filled": false,
            "author_pub_id": "mF4nMFoAAAAJ:yD5IFk8b50cC",
            "num_citations": 1,
            "citedby_url": "https://scholar.google.com/scholar?oi=bibs&hl=en&cites=7450503319948303841",
            "cites_id": [
                "7450503319948303841"
            ]
        },
        {
            "container_type": "Publication",
            "source": "AUTHOR_PUBLICATION_ENTRY",
            "bib": {
                "title": "Pandemia de influenza por el nuevo virus A (H1N1) 2009 en Chile:\u00bf C\u00f3mo hemos vivido esta primera ola?",
                "pub_year": "2009",
                "citation": "Revista chilena de infectolog\u00eda 26 (4), 307-308, 2009"
            },
            "filled": false,
            "author_pub_id": "mF4nMFoAAAAJ:qxL8FJ1GzNcC",
            "num_citations": 1,
            "citedby_url": "https://scholar.google.com/scholar?oi=bibs&hl=en&cites=6784260470662028911",
            "cites_id": [
                "6784260470662028911"
            ]
        },
        {
            "container_type": "Publication",
            "source": "AUTHOR_PUBLICATION_ENTRY",
            "bib": {
                "title": "Pertussis vaccine for adolescents and adults",
                "pub_year": "2006",
                "citation": "Revista Chilena de Infectologia: Organo Oficial de la Sociedad Chilena de \u2026, 2006"
            },
            "filled": false,
            "author_pub_id": "mF4nMFoAAAAJ:5Ul4iDaHHb8C",
            "num_citations": 1,
            "citedby_url": "https://scholar.google.com/scholar?oi=bibs&hl=en&cites=14523498650812194317",
            "cites_id": [
                "14523498650812194317"
            ]
        },
        {
            "container_type": "Publication",
            "source": "AUTHOR_PUBLICATION_ENTRY",
            "bib": {
                "title": "Guidelines for management of animal bites",
                "pub_year": "2006",
                "citation": "Revista Chilena de Infectologia: Organo Oficial de la Sociedad Chilena de \u2026, 2006"
            },
            "filled": false,
            "author_pub_id": "mF4nMFoAAAAJ:4fKUyHm3Qg0C",
            "num_citations": 1,
            "citedby_url": "https://scholar.google.com/scholar?oi=bibs&hl=en&cites=4070552705987857290",
            "cites_id": [
                "4070552705987857290"
            ]
        },
        {
            "container_type": "Publication",
            "source": "AUTHOR_PUBLICATION_ENTRY",
            "bib": {
                "title": "Non-typable Haemophilus influenzae severe pneumonia in an infant: case report",
                "pub_year": "2005",
                "citation": "Revista Chilena de Infectologia: Organo Oficial de la Sociedad Chilena de \u2026, 2005"
            },
            "filled": false,
            "author_pub_id": "mF4nMFoAAAAJ:Y0pCki6q_DkC",
            "num_citations": 1,
            "citedby_url": "https://scholar.google.com/scholar?oi=bibs&hl=en&cites=1616200040395402365",
            "cites_id": [
                "1616200040395402365"
            ]
        },
        {
            "container_type": "Publication",
            "source": "AUTHOR_PUBLICATION_ENTRY",
            "bib": {
                "title": "Varicella complications requiring hospitalization in four hospitals in Santiago, Chile: clinical spectrum and estimation of direct costs.",
                "pub_year": "2001",
                "citation": ""
            },
            "filled": false,
            "author_pub_id": "mF4nMFoAAAAJ:eMMeJKvmdy0C",
            "num_citations": 1,
            "citedby_url": "https://scholar.google.com/scholar?oi=bibs&hl=en&cites=11444631603273645409",
            "cites_id": [
                "11444631603273645409"
            ]
        },
        {
            "container_type": "Publication",
            "source": "AUTHOR_PUBLICATION_ENTRY",
            "bib": {
                "title": "Meningitis bacteriana aguda por streptococcus pyogenes: caso cl\u00ednico y revisi\u00f3n de la literatura",
                "pub_year": "2000",
                "citation": "Rev. chil. infectol, 135-8, 2000"
            },
            "filled": false,
            "author_pub_id": "mF4nMFoAAAAJ:KlAtU1dfN6UC",
            "num_citations": 1,
            "citedby_url": "https://scholar.google.com/scholar?oi=bibs&hl=en&cites=5540410534163370500",
            "cites_id": [
                "5540410534163370500"
            ]
        },
        {
            "container_type": "Publication",
            "source": "AUTHOR_PUBLICATION_ENTRY",
            "bib": {
                "title": "Shock t\u00f3xico por estreptococo \u00df-hemol\u00edtico grupo A en pediatr\u00eda",
                "pub_year": "1997",
                "citation": "Pediatr. d\u00eda, 269-72, 1997"
            },
            "filled": false,
            "author_pub_id": "mF4nMFoAAAAJ:hqOjcs7Dif8C",
            "num_citations": 1,
            "citedby_url": "https://scholar.google.com/scholar?oi=bibs&hl=en&cites=10118425496736676452",
            "cites_id": [
                "10118425496736676452"
            ]
        },
        {
            "container_type": "Publication",
            "source": "AUTHOR_PUBLICATION_ENTRY",
            "bib": {
                "title": "Immune responses during COVID-19 breakthrough cases in vaccinated children and adolescents",
                "pub_year": "2024",
                "citation": "Frontiers in Immunology 15, 1372193, 2024"
            },
            "filled": false,
            "author_pub_id": "mF4nMFoAAAAJ:dTyEYWd-f8wC",
            "num_citations": 0
        },
        {
            "container_type": "Publication",
            "source": "AUTHOR_PUBLICATION_ENTRY",
            "bib": {
                "title": "Interferon 1beta-1a ring prophylaxis to reduce household transmission of SARS-CoV-2",
                "pub_year": "2023",
                "citation": "Respirology, 108-108, 2023"
            },
            "filled": false,
            "author_pub_id": "mF4nMFoAAAAJ:eflP2zaiRacC",
            "num_citations": 0
        },
        {
            "container_type": "Publication",
            "source": "AUTHOR_PUBLICATION_ENTRY",
            "bib": {
                "title": "Emerging infections in children",
                "pub_year": "2023",
                "citation": "Frontiers in Pediatrics 11, 2023"
            },
            "filled": false,
            "author_pub_id": "mF4nMFoAAAAJ:fQNAKQ3IYiAC",
            "num_citations": 0
        },
        {
            "container_type": "Publication",
            "source": "AUTHOR_PUBLICATION_ENTRY",
            "bib": {
                "title": "Clinical and epidemiological characteristics of SARS-CoV-2 virus in ambulatory children under 2 years old",
                "pub_year": "2022",
                "citation": "Frontiers in Pediatrics 10, 957273, 2022"
            },
            "filled": false,
            "author_pub_id": "mF4nMFoAAAAJ:08ZZubdj9fEC",
            "num_citations": 0
        },
        {
            "container_type": "Publication",
            "source": "AUTHOR_PUBLICATION_ENTRY",
            "bib": {
                "title": "Interferon Beta-1\u03b1 ring prophylaxis to reduce household transmission of SARS-CoV-2: the Containing Coronavirus Disease-19 randomized clinical trial",
                "pub_year": "2022",
                "citation": "medRxiv, 2022.06. 13.22276369, 2022"
            },
            "filled": false,
            "author_pub_id": "mF4nMFoAAAAJ:Tiz5es2fbqcC",
            "num_citations": 0
        },
        {
            "container_type": "Publication",
            "source": "AUTHOR_PUBLICATION_ENTRY",
            "bib": {
                "title": "Interferon Beta-1\u03b1 ring prophylaxis to reduce household transmission of SARS-CoV-2 (preprint)",
                "pub_year": "2022",
                "citation": ""
            },
            "filled": false,
            "author_pub_id": "mF4nMFoAAAAJ:tOudhMTPpwUC",
            "num_citations": 0
        },
        {
            "container_type": "Publication",
            "source": "AUTHOR_PUBLICATION_ENTRY",
            "bib": {
                "title": "Emergent Pneumonia in Children",
                "pub_year": "2021",
                "citation": ""
            },
            "filled": false,
            "author_pub_id": "mF4nMFoAAAAJ:9vf0nzSNQJEC",
            "num_citations": 0
        },
        {
            "container_type": "Publication",
            "source": "AUTHOR_PUBLICATION_ENTRY",
            "bib": {
                "title": "Bartonella henselae with atypical infection and neuroretinitis in a pediatric unit: report of three cases",
                "pub_year": "2020",
                "citation": "Revista chilena de infectologia: organo oficial de la Sociedad Chilena de \u2026, 2020"
            },
            "filled": false,
            "author_pub_id": "mF4nMFoAAAAJ:b0M2c_1WBrUC",
            "num_citations": 0
        },
        {
            "container_type": "Publication",
            "source": "AUTHOR_PUBLICATION_ENTRY",
            "bib": {
                "title": "Modelo computacional interactivo, semi automatizado y de c\u00f3digo abierto aplicado a la Vigilancia de Virus Respiratorios",
                "pub_year": "2020",
                "citation": "Revista Chilena de Infectolog\u00eda 1 (1), 2020"
            },
            "filled": false,
            "author_pub_id": "mF4nMFoAAAAJ:TFP_iSt0sucC",
            "num_citations": 0
        },
        {
            "container_type": "Publication",
            "source": "AUTHOR_PUBLICATION_ENTRY",
            "bib": {
                "title": "Interactive, semi-automatized and open source computational model applied to respiratory viruses surveillance",
                "pub_year": "2020",
                "citation": "Revista Chilena de Infectologia: Organo Oficial de la Sociedad Chilena de \u2026, 2020"
            },
            "filled": false,
            "author_pub_id": "mF4nMFoAAAAJ:roLk4NBRz8UC",
            "num_citations": 0
        },
        {
            "container_type": "Publication",
            "source": "AUTHOR_PUBLICATION_ENTRY",
            "bib": {
                "title": "Modelo computacional interactivo, semi-automatizado y de c\u00f3digo abierto aplicado a la vigilancia de virus respiratorios",
                "pub_year": "2020",
                "citation": ""
            },
            "filled": false,
            "author_pub_id": "mF4nMFoAAAAJ:mvPsJ3kp5DgC",
            "num_citations": 0
        },
        {
            "container_type": "Publication",
            "source": "AUTHOR_PUBLICATION_ENTRY",
            "bib": {
                "title": "Study of Infectious Agents in Respiratory Diseases",
                "pub_year": "2020",
                "citation": "Pediatric Respiratory Diseases: A Comprehensive Textbook, 145-150, 2020"
            },
            "filled": false,
            "author_pub_id": "mF4nMFoAAAAJ:SeFeTyx0c_EC",
            "num_citations": 0
        },
        {
            "container_type": "Publication",
            "source": "AUTHOR_PUBLICATION_ENTRY",
            "bib": {
                "title": "Laryngitis (Croup)",
                "pub_year": "2020",
                "citation": "Pediatric Respiratory Diseases: A Comprehensive Textbook, 273-281, 2020"
            },
            "filled": false,
            "author_pub_id": "mF4nMFoAAAAJ:TQgYirikUcIC",
            "num_citations": 0
        },
        {
            "container_type": "Publication",
            "source": "AUTHOR_PUBLICATION_ENTRY",
            "bib": {
                "title": "Evaluaci\u00f3n del uso y monitoreo de amikacina en pacientes pedi\u00e1tricos hospitalizados en los servicio de pediatr\u00eda y UPCP del HCUC entre febrero y julio de 2017.",
                "pub_year": "2019",
                "citation": ""
            },
            "filled": false,
            "author_pub_id": "mF4nMFoAAAAJ:9yKSN-GCB0IC",
            "num_citations": 0
        },
        {
            "container_type": "Publication",
            "source": "AUTHOR_PUBLICATION_ENTRY",
            "bib": {
                "title": "Chikungunya, enfermedad emergente en Am\u00e9rica Latina. Descripci\u00f3n de los primeros casos en Chile",
                "pub_year": "2018",
                "citation": ""
            },
            "filled": false,
            "author_pub_id": "mF4nMFoAAAAJ:V3AGJWp-ZtQC",
            "num_citations": 0
        },
        {
            "container_type": "Publication",
            "source": "AUTHOR_PUBLICATION_ENTRY",
            "bib": {
                "title": "Chikungunya, emerging disease in Latin America. Description of the first cases in Chile",
                "pub_year": "2018",
                "citation": ""
            },
            "filled": false,
            "author_pub_id": "mF4nMFoAAAAJ:kRWSkSYxWN8C",
            "num_citations": 0
        },
        {
            "container_type": "Publication",
            "source": "AUTHOR_PUBLICATION_ENTRY",
            "bib": {
                "title": "Yellow fever vaccination for chilean tourists visiting Brazil. Practical considerations [Vacuna contra fiebre amarilla para viajeros chilenos a Brasil. Consideraciones pr\u00e1cticas]",
                "pub_year": "2018",
                "citation": ""
            },
            "filled": false,
            "author_pub_id": "mF4nMFoAAAAJ:LPZeul_q3PIC",
            "num_citations": 0
        },
        {
            "container_type": "Publication",
            "source": "AUTHOR_PUBLICATION_ENTRY",
            "bib": {
                "title": "Chikungunya, enfermedad emergente en Am  rica Latina. Descripci  n de los primeros casos en Chile [Chikungunya, emerging disease in Latin America. Description of the first \u2026",
                "pub_year": "2018",
                "citation": ""
            },
            "filled": false,
            "author_pub_id": "mF4nMFoAAAAJ:R3hNpaxXUhUC",
            "num_citations": 0
        },
        {
            "container_type": "Publication",
            "source": "AUTHOR_PUBLICATION_ENTRY",
            "bib": {
                "title": "Zika Virus Infection in a Non-Mosquito-Borne Transmission Country",
                "pub_year": "2016",
                "citation": "Open Forum Infectious Diseases 3 (suppl_1), 603, 2016"
            },
            "filled": false,
            "author_pub_id": "mF4nMFoAAAAJ:Zph67rFs4hoC",
            "num_citations": 0
        },
        {
            "container_type": "Publication",
            "source": "AUTHOR_PUBLICATION_ENTRY",
            "bib": {
                "title": "What is human infection with Zika virus?",
                "pub_year": "2016",
                "citation": "Revista Medica de Chile 144 (10), 1322-1325, 2016"
            },
            "filled": false,
            "author_pub_id": "mF4nMFoAAAAJ:kNdYIx-mwKoC",
            "num_citations": 0
        },
        {
            "container_type": "Publication",
            "source": "AUTHOR_PUBLICATION_ENTRY",
            "bib": {
                "title": "Imported Cases in Continental Chile and Autochthonous In Easter Island",
                "pub_year": "2016",
                "citation": "Current Topics in Chikungunya, 2016"
            },
            "filled": false,
            "author_pub_id": "mF4nMFoAAAAJ:YsMSGLbcyi4C",
            "num_citations": 0
        },
        {
            "container_type": "Publication",
            "source": "AUTHOR_PUBLICATION_ENTRY",
            "bib": {
                "title": "Aporte de la biolog\u00eda molecular en el diagn\u00f3stico de infecciones respiratorias agudas",
                "pub_year": "2016",
                "citation": ""
            },
            "filled": false,
            "author_pub_id": "mF4nMFoAAAAJ:1qzjygNMrQYC",
            "num_citations": 0
        },
        {
            "container_type": "Publication",
            "source": "AUTHOR_PUBLICATION_ENTRY",
            "bib": {
                "title": "\u00bf En qu\u00e9 consiste la infecci\u00f3n humana por virus Zika?",
                "pub_year": "2016",
                "citation": ""
            },
            "filled": false,
            "author_pub_id": "mF4nMFoAAAAJ:pqnbT2bcN3wC",
            "num_citations": 0
        },
        {
            "container_type": "Publication",
            "source": "AUTHOR_PUBLICATION_ENTRY",
            "bib": {
                "title": "Pediatric Respiratory Diseases.",
                "pub_year": "2016",
                "citation": "Santiago de Chile: Springer, 2016"
            },
            "filled": false,
            "author_pub_id": "mF4nMFoAAAAJ:bEWYMUwI8FkC",
            "num_citations": 0
        },
        {
            "container_type": "Publication",
            "source": "AUTHOR_PUBLICATION_ENTRY",
            "bib": {
                "title": "Recomendaciones para viajeros chilenos a la Copa Mundial de la FIFA 2014 en Brasil",
                "pub_year": "2014",
                "citation": "Revista chilena de infectolog\u00eda 31 (2), 207-208, 2014"
            },
            "filled": false,
            "author_pub_id": "mF4nMFoAAAAJ:M3NEmzRMIkIC",
            "num_citations": 0
        },
        {
            "container_type": "Publication",
            "source": "AUTHOR_PUBLICATION_ENTRY",
            "bib": {
                "title": "Infecciones en viajeros internacionales",
                "pub_year": "2014",
                "citation": ""
            },
            "filled": false,
            "author_pub_id": "mF4nMFoAAAAJ:e5wmG9Sq2KIC",
            "num_citations": 0
        },
        {
            "container_type": "Publication",
            "source": "AUTHOR_PUBLICATION_ENTRY",
            "bib": {
                "title": "Many Respiratory Viruses May Trigger Meningococcal Diseases",
                "pub_year": "2011",
                "citation": "C59. H1N1 INFLUENZA AND OTHER VIRAL INFECTIONS: CLINICAL MANIFESTATIONS \u2026, 2011"
            },
            "filled": false,
            "author_pub_id": "mF4nMFoAAAAJ:Tyk-4Ss8FVUC",
            "num_citations": 0
        },
        {
            "container_type": "Publication",
            "source": "AUTHOR_PUBLICATION_ENTRY",
            "bib": {
                "title": "Clinical and epidemiology characterization of children hospitalized with influenza A H1N1 (FLU AH1N1) during the first wave of 2009 outbreak, Santiago, Chile",
                "pub_year": "2010",
                "citation": "International Journal of Infectious Diseases 14, e423-e424, 2010"
            },
            "filled": false,
            "author_pub_id": "mF4nMFoAAAAJ:bFI3QPDXJZMC",
            "num_citations": 0
        },
        {
            "container_type": "Publication",
            "source": "AUTHOR_PUBLICATION_ENTRY",
            "bib": {
                "title": "Traveling with Kids",
                "pub_year": "2010",
                "citation": "International Journal of Infectious Diseases 14, e3, 2010"
            },
            "filled": false,
            "author_pub_id": "mF4nMFoAAAAJ:f2IySw72cVMC",
            "num_citations": 0
        },
        {
            "container_type": "Publication",
            "source": "AUTHOR_PUBLICATION_ENTRY",
            "bib": {
                "title": "Cutaneous Diseases in Returnee Travellers from Latin America",
                "pub_year": "2010",
                "citation": "International Journal of Infectious Diseases 14, e172, 2010"
            },
            "filled": false,
            "author_pub_id": "mF4nMFoAAAAJ:4OULZ7Gr8RgC",
            "num_citations": 0
        },
        {
            "container_type": "Publication",
            "source": "AUTHOR_PUBLICATION_ENTRY",
            "bib": {
                "title": "Circulaci\u00f3n de los virus influenza durante la primera ola pand\u00e9mica en Chile",
                "pub_year": "2010",
                "citation": "Vig\u00eda (Santiago), 10-13, 2010"
            },
            "filled": false,
            "author_pub_id": "mF4nMFoAAAAJ:J_g5lzvAfSwC",
            "num_citations": 0
        },
        {
            "container_type": "Publication",
            "source": "AUTHOR_PUBLICATION_ENTRY",
            "bib": {
                "title": "Pandemic risk of Avian Influenza",
                "pub_year": "2008",
                "citation": "REVISTA CHILENA DE PEDIATRIA-CHILE 79 (4), 358-363, 2008"
            },
            "filled": false,
            "author_pub_id": "mF4nMFoAAAAJ:XiSMed-E-HIC",
            "num_citations": 0
        },
        {
            "container_type": "Publication",
            "source": "AUTHOR_PUBLICATION_ENTRY",
            "bib": {
                "title": "Protocolo prevenci\u00f3n y control del dengue",
                "pub_year": "2007",
                "citation": "Protocolo prevenci\u00f3n y control del dengue, 38-38, 2007"
            },
            "filled": false,
            "author_pub_id": "mF4nMFoAAAAJ:NaGl4SEjCO4C",
            "num_citations": 0
        },
        {
            "container_type": "Publication",
            "source": "AUTHOR_PUBLICATION_ENTRY",
            "bib": {
                "title": "Malaria: report of 12 non autochthonous cases",
                "pub_year": "2006",
                "citation": "Revista Medica de Chile 134 (4), 421-425, 2006"
            },
            "filled": false,
            "author_pub_id": "mF4nMFoAAAAJ:8AbLer7MMksC",
            "num_citations": 0
        },
        {
            "container_type": "Publication",
            "source": "AUTHOR_PUBLICATION_ENTRY",
            "bib": {
                "title": "Cu\u00e1les son las caracter\u00edsticas de esta nueva enfermedad llamada SARS",
                "pub_year": "2003",
                "citation": "Revista chilena de pediatr\u00eda 74 (3), 308-310, 2003"
            },
            "filled": false,
            "author_pub_id": "mF4nMFoAAAAJ:g5m5HwL7SMYC",
            "num_citations": 0
        },
        {
            "container_type": "Publication",
            "source": "AUTHOR_PUBLICATION_ENTRY",
            "bib": {
                "title": "\u00bf Cu\u00e1les son las caracter\u00edsticas de esta nueva enfermedad llamada SARS?",
                "pub_year": "2003",
                "citation": ""
            },
            "filled": false,
            "author_pub_id": "mF4nMFoAAAAJ:SdhP9T11ey4C",
            "num_citations": 0
        },
        {
            "container_type": "Publication",
            "source": "AUTHOR_PUBLICATION_ENTRY",
            "bib": {
                "title": "What are the characteristics of this new disease SARS?",
                "pub_year": "2003",
                "citation": "REVISTA CHILENA DE PEDIATRIA 74 (3), 308-310, 2003"
            },
            "filled": false,
            "author_pub_id": "mF4nMFoAAAAJ:pyW8ca7W8N0C",
            "num_citations": 0
        },
        {
            "container_type": "Publication",
            "source": "AUTHOR_PUBLICATION_ENTRY",
            "bib": {
                "title": "Antrax",
                "pub_year": "2001",
                "citation": "Rev. chil. infectol, 291-299, 2001"
            },
            "filled": false,
            "author_pub_id": "mF4nMFoAAAAJ:LjlpjdlvIbIC",
            "num_citations": 0
        },
        {
            "container_type": "Publication",
            "source": "AUTHOR_PUBLICATION_ENTRY",
            "bib": {
                "title": "Resistant Streptococcus pneumoniae in pediatrics. Current concepts",
                "pub_year": "2001",
                "citation": "REVISTA CHILENA DE PEDIATRIA 72 (1), 49-51, 2001"
            },
            "filled": false,
            "author_pub_id": "mF4nMFoAAAAJ:D03iK_w7-QYC",
            "num_citations": 0
        },
        {
            "container_type": "Publication",
            "source": "AUTHOR_PUBLICATION_ENTRY",
            "bib": {
                "title": "EVALUATION OF DIAGNOSTIC METHODS FOR CONGENITAL SYPHILIS",
                "pub_year": "2000",
                "citation": "Rev. chil. infectol 17 (4), 289-296, 2000"
            },
            "filled": false,
            "author_pub_id": "mF4nMFoAAAAJ:NMxIlDl6LWMC",
            "num_citations": 0
        },
        {
            "container_type": "Publication",
            "source": "AUTHOR_PUBLICATION_ENTRY",
            "bib": {
                "title": "Ventilaci\u00f3n oscilatoria de alta frecuencia en ni\u00f1os con s\u00edndrome de dificultad respiratoria tipo adulto",
                "pub_year": "2000",
                "citation": "Arch. argent. pediatr 98 (3), 175, 2000"
            },
            "filled": false,
            "author_pub_id": "mF4nMFoAAAAJ:k_IJM867U9cC",
            "num_citations": 0
        },
        {
            "container_type": "Publication",
            "source": "AUTHOR_PUBLICATION_ENTRY",
            "bib": {
                "title": "Etiolog\u00eda del s\u00edndrome coquelucho\u00eddeo y rendimiento de las t\u00e9cnicas para el diagn\u00f3stico de bordetella pertussis en pacientes hospitalizados",
                "pub_year": "1999",
                "citation": "Rev. chil. infectol, 17-26, 1999"
            },
            "filled": false,
            "author_pub_id": "mF4nMFoAAAAJ:WqliGbK-hY8C",
            "num_citations": 0
        },
        {
            "container_type": "Publication",
            "source": "AUTHOR_PUBLICATION_ENTRY",
            "bib": {
                "title": "Comparison of 2 methods of determining the sweat test in the diagnosis of cystic fibrosis",
                "pub_year": "1999",
                "citation": "REVISTA CHILENA DE PEDIATRIA 70, 281-287, 1999"
            },
            "filled": false,
            "author_pub_id": "mF4nMFoAAAAJ:EUQCXRtRnyEC",
            "num_citations": 0
        },
        {
            "container_type": "Publication",
            "source": "AUTHOR_PUBLICATION_ENTRY",
            "bib": {
                "title": "Dengue",
                "pub_year": "1999",
                "citation": "Rev. chil. infectol, 220-4, 1999"
            },
            "filled": false,
            "author_pub_id": "mF4nMFoAAAAJ:3fE2CSJIrl8C",
            "num_citations": 0
        },
        {
            "container_type": "Publication",
            "source": "AUTHOR_PUBLICATION_ENTRY",
            "bib": {
                "title": "Neumococo resistente a la penicilina",
                "pub_year": "1998",
                "citation": "Pediatr. d\u00eda, 35-9, 1998"
            },
            "filled": false,
            "author_pub_id": "mF4nMFoAAAAJ:8k81kl-MbHgC",
            "num_citations": 0
        },
        {
            "container_type": "Publication",
            "source": "AUTHOR_PUBLICATION_ENTRY",
            "bib": {
                "title": "Neumon\u00eda por citomegalovirus y linfoma de Burkitt: caso cl\u00ednico y discusi\u00f3n de la literatura",
                "pub_year": "1995",
                "citation": "Rev. chil. infectol, 216-22, 1995"
            },
            "filled": false,
            "author_pub_id": "mF4nMFoAAAAJ:QIV2ME_5wuYC",
            "num_citations": 0
        },
        {
            "container_type": "Publication",
            "source": "AUTHOR_PUBLICATION_ENTRY",
            "bib": {
                "title": "Thrombose veineuse du sujet jeune importance de la recherche des d\u00e9ficits en inhibiteurs de la coagulation et des hypofibrinolyses: \u00e0 propos d'une observation d'un d\u00e9ficit \u2026",
                "pub_year": "1986",
                "citation": "Journal de m\u00e9decine de Strasbourg 17 (8), 465-469, 1986"
            },
            "filled": false,
            "author_pub_id": "mF4nMFoAAAAJ:_xSYboBqXhAC",
            "num_citations": 0
        },
        {
            "container_type": "Publication",
            "source": "AUTHOR_PUBLICATION_ENTRY",
            "bib": {
                "title": "Clinical Manifestations",
                "citation": ""
            },
            "filled": false,
            "author_pub_id": "mF4nMFoAAAAJ:IWHjjKOFINEC",
            "num_citations": 0
        },
        {
            "container_type": "Publication",
            "source": "AUTHOR_PUBLICATION_ENTRY",
            "bib": {
                "title": "ARTICULO ORIGINAL VENTILACION OSCILATORIA DE ALTA FRECUENCIA EN NI\u00d1OS CON SINDROME DE DIFICULTAD RESPIRATORIA \u00abDEL ADULTO\u00bb",
                "citation": ""
            },
            "filled": false,
            "author_pub_id": "mF4nMFoAAAAJ:5nxA0vEk-isC",
            "num_citations": 0
        }
    ],
    "public_access": {
        "available": 8,
        "not_available": 1
    }
}